pocketrockit/__init__.py
pocketrockit/cli.py
pocketrockit/commons.py
pocketrockit/decorated.py
pocketrockit/engine.py
pocketrockit/examples/pocketrockit.toml
pocketrockit/examples/template.py
pocketrockit/midi_io.py
pocketrockit/misc.py
pocketrockit-0.0.31.dist-info/METADATA
pocketrockit-0.0.31.dist-info/WHEEL
pocketrockit-0.0.31.dist-info/entry_points.txt
pocketrockit-0.0.31.dist-info/RECORD
