Metadata-Version: 2.1
Name: pocketrockit
Version: 0.0.31
Summary: Live music coding inspired by Sonic Pi
Home-page: https://projects.om-office.de/frans/pocketrockit.git
Author: Frans Fürst
Author-email: frans.fuerst+gitlab@protonmail.com
Requires-Python: >=3.9,<4.0
Classifier: Programming Language :: Python :: 3
Classifier: Programming Language :: Python :: 3.9
Classifier: Programming Language :: Python :: 3.10
Classifier: Programming Language :: Python :: 3.11
Requires-Dist: asyncinotify (>=4.0.1,<5.0.0)
Requires-Dist: pyfluidsynth (>=1.3.1,<2.0.0)
Requires-Dist: pygame (>=2.3.0,<3.0.0)
Requires-Dist: sf2utils (>=0.9.0,<0.10.0)
Requires-Dist: textual (>=0.25.0,<0.26.0)
Requires-Dist: toml (>=0.10.2,<0.11.0)
Project-URL: Repository, https://projects.om-office.de/frans/pocketrockit.git
